magic_links/__init__.py
magic_links/__version__.py
magic_links/admin.py
magic_links/apps.py
magic_links/constants.py
magic_links/exceptions.py
magic_links/models.py
magic_links/serializers.py
magic_links/services.py
magic_links/settings.py
magic_links/utils.py
magic_links/migrations/0001_initial.py
magic_links/migrations/__init__.py
magic_links/urls/__init__.py
magic_links/urls/api.py
magic_links/views/__init__.py
magic_links/views/api.py
drf_magic_links-1.0.0.dist-info/LICENSE.txt
drf_magic_links-1.0.0.dist-info/METADATA
drf_magic_links-1.0.0.dist-info/WHEEL
drf_magic_links-1.0.0.dist-info/top_level.txt
drf_magic_links-1.0.0.dist-info/RECORD
