Metadata-Version: 2.1
Name: drf-magic-links
Version: 1.0.0
Summary: UNKNOWN
Home-page: https://github.com/null-none/drf-magic-links
Author: Kalinin Mitko
Author-email: kalinin.mitko@gmail.com
License: UNKNOWN
Platform: UNKNOWN
License-File: LICENSE.txt
Requires-Dist: bcrypt
Requires-Dist: django-rest-framework
